QuantNado/__init__.py
QuantNado/_version.py
QuantNado/call_quantile_peaks.py
QuantNado/cli.py
QuantNado/make_dataset.py
quantnado-0.2.5.dist-info/licenses/LICENSE
quantnado-0.2.5.dist-info/METADATA
quantnado-0.2.5.dist-info/WHEEL
quantnado-0.2.5.dist-info/entry_points.txt
quantnado-0.2.5.dist-info/top_level.txt
quantnado-0.2.5.dist-info/RECORD
