Metadata-Version: 2.4
Name: QuantNado
Version: 0.2.5
Summary: Quantile-based peak calling from RPKM bigWig files
Author-email: Catherine Chahrour <your.email@example.com>
License-Expression: MIT
Requires-Python: >=3.8
License-File: LICENSE
Requires-Dist: crested
Requires-Dist: loguru
Requires-Dist: numpy
Requires-Dist: pandas
Requires-Dist: pyranges
Requires-Dist: torch
Requires-Dist: modisco-lite
Provides-Extra: dev
Requires-Dist: pytest; extra == "dev"
Dynamic: license-file
